pyoneai_ops/__init__.py
pyoneai_ops/io.py
pyoneai_ops/logger.py
pyoneai_ops/insight/__init__.py
pyoneai_ops/insight/api_v1.py
pyoneai_ops/insight/collector.py
pyoneai_ops/insight/config.py
pyoneai_ops/insight/main.py
pyoneai_ops/insight/server.py
pyoneai_ops/mlops/__init__.py
pyoneai_ops/mlops/config.py
pyoneai_ops/mlops/const.py
pyoneai_ops/mlops/dataset.py
pyoneai_ops/mlops/metrics.py
pyoneai_ops/mlops/types.py
pyoneai_ops/mlops/core/data.py
pyoneai_ops/mlops/core/evaluation.py
pyoneai_ops/mlops/core/models.py
pyoneai_ops/mlops/core/reporting.py
pyoneai_ops/mlops/core/training.py
pyoneai_ops/mlops/core/utils.py
pyoneai_ops/mlops/drivers/__init__.py
pyoneai_ops/mlops/drivers/base.py
pyoneai_ops/mlops/drivers/lightning.py
pyoneai_ops/mlops/drivers/persistencemodel.py
pyoneai_ops/mlops/drivers/statsmodels.py
pyoneai_ops/mlops/generators/__init__.py
pyoneai_ops/mlops/generators/real.py
pyoneai_ops/mlops/generators/synthetic.py
pyoneai_ops/mlops/generators/utils/date_utils.py
pyoneai_ops/mlops/generators/utils/utils.py
pyoneai_ops/mlops/setup/__init__.py
pyoneai_ops/mlops/setup/__main__.py
pyoneai_ops/mlops/setup/queues.py
pyoneai_ops/mlops/setup/training.py
pyoneai_ops/mlops/setup/variables.py
pyoneai_ops/mlops/setup/work_pools.py
pyoneai_ops/mlops/workflows/__init__.py
pyoneai_ops/mlops/workflows/data.py
pyoneai_ops/mlops/workflows/evaluation.py
pyoneai_ops/mlops/workflows/models.py
pyoneai_ops/mlops/workflows/persistance.py
pyoneai_ops/mlops/workflows/reporting.py
pyoneai_ops/mlops/workflows/setup.py
pyoneai_ops/mlops/workflows/utils.py
pyoneai_ops/orchestrator/__init__.py
pyoneai_ops/orchestrator/mapper/__init__.py
pyoneai_ops/orchestrator/mapper/ilp_optimizer.py
pyoneai_ops/orchestrator/mapper/mapper.py
pyoneai_ops/orchestrator/plan_executor/__init__.py
pyoneai_ops/orchestrator/plan_executor/api_v1.py
pyoneai_ops/orchestrator/plan_executor/config.py
pyoneai_ops/orchestrator/plan_executor/drivers.py
pyoneai_ops/orchestrator/plan_executor/exception.py
pyoneai_ops-0.2.dist-info/LICENSE
pyoneai_ops-0.2.dist-info/METADATA
pyoneai_ops-0.2.dist-info/WHEEL
pyoneai_ops-0.2.dist-info/top_level.txt
pyoneai_ops-0.2.dist-info/RECORD
